README.md
setup.cfg
setup.py
avtf_api_joke/__init__.py
avtf_api_joke/my_code.py
avtf_api_joke/second_code.py
avtf_api_joke.egg-info/PKG-INFO
avtf_api_joke.egg-info/SOURCES.txt
avtf_api_joke.egg-info/dependency_links.txt
avtf_api_joke.egg-info/top_level.txt